cardo_python_utils-0.4.1.dist-info/licenses/LICENSE
python_utils/__init__.py
python_utils/choices.py
python_utils/data_structures.py
python_utils/db.py
python_utils/django_utils.py
python_utils/esma_choices.py
python_utils/exceptions.py
python_utils/imports.py
python_utils/math.py
python_utils/pandas_utils.py
python_utils/rest.py
python_utils/text.py
python_utils/time.py
python_utils/types_hinting.py
cardo_python_utils-0.4.1.dist-info/METADATA
cardo_python_utils-0.4.1.dist-info/WHEEL
cardo_python_utils-0.4.1.dist-info/top_level.txt
cardo_python_utils-0.4.1.dist-info/RECORD
