Metadata-Version: 2.4
Name: cardo-python-utils
Version: 0.4.1
Summary: Python library enhanced with a wide range of functions for different scenarios.
Home-page: https://github.com/CardoAI/cardo-python-utils
Author: Kristi Kotini
Author-email: hello@cardoai.com
License: MIT (X11)
Classifier: Environment :: Web Environment
Classifier: Framework :: Django
Classifier: Intended Audience :: Developers
Classifier: License :: OSI Approved :: BSD License
Classifier: Operating System :: OS Independent
Classifier: Programming Language :: Python
Classifier: Programming Language :: Python :: 3
Classifier: Programming Language :: Python :: 3 :: Only
Classifier: Programming Language :: Python :: 3.8
Classifier: Programming Language :: Python :: 3.9
Classifier: Programming Language :: Python :: 3.10
Classifier: Topic :: Internet :: WWW/HTTP
Classifier: Topic :: Internet :: WWW/HTTP :: Dynamic Content
Requires-Python: >=3.8
License-File: LICENSE
Provides-Extra: pandas
Requires-Dist: pandas>=1.4.0; extra == "pandas"
Provides-Extra: django
Requires-Dist: Django; extra == "django"
Requires-Dist: django-model-utils==4.2.0; extra == "django"
Provides-Extra: rest
Requires-Dist: djangorestframework; extra == "rest"
Requires-Dist: requests; extra == "rest"
Provides-Extra: all
Requires-Dist: Django; extra == "all"
Requires-Dist: pandas>=1.4.0; extra == "all"
Requires-Dist: django-model-utils>=4.2.0; extra == "all"
Requires-Dist: djangorestframework; extra == "all"
Requires-Dist: requests; extra == "all"
Dynamic: license-file
